pyblobby3d/__init__.py
pyblobby3d/b3dcomp.py
pyblobby3d/b3dplot.py
pyblobby3d/const.py
pyblobby3d/meta.py
pyblobby3d/moments.py
pyblobby3d/post_blobby3d.py
pyblobby3d/pre_blobby3d.py
pyblobby3d-0.0.2.dist-info/METADATA
pyblobby3d-0.0.2.dist-info/WHEEL
pyblobby3d-0.0.2.dist-info/top_level.txt
pyblobby3d-0.0.2.dist-info/RECORD
